RTRTC/PyRTRTC.dll
RTRTC/__init__.py
RTRTC/libPyRTRTC.so
RTRTC-0.1.6.dist-info/METADATA
RTRTC-0.1.6.dist-info/WHEEL
RTRTC-0.1.6.dist-info/top_level.txt
RTRTC-0.1.6.dist-info/RECORD
