Metadata-Version: 2.1
Name: RTRTC
Version: 0.1.6
Summary: Toy ray-tracer based on ThrustRTC on CURandRTC
Home-page: https://github.com/fynv/RTRTC
Author: Fei Yang
Author-email: hyangfeih@gmail.com
License: Anti 996
Keywords: GPU CUDA RayTracing
Platform: UNKNOWN
Requires-Dist: CURandRTC
Requires-Dist: ThrustRTC
Requires-Dist: numpy
Requires-Dist: pillow
